kandula/__init__.py
kandula/q_learning.py
kandula/qtable.py
kandula/steps.py
kandula-0.0.2.dist-info/LICENSE
kandula-0.0.2.dist-info/METADATA
kandula-0.0.2.dist-info/WHEEL
kandula-0.0.2.dist-info/RECORD
